DeepMap/__init__.py
DeepMap/main.py
DeepMap-1.1.dist-info/LICENCE.txt
DeepMap-1.1.dist-info/METADATA
DeepMap-1.1.dist-info/WHEEL
DeepMap-1.1.dist-info/top_level.txt
DeepMap-1.1.dist-info/RECORD
