Metadata-Version: 2.1
Name: DeepMap
Version: 1.1
Summary: The DeepMap is a deep learning based python package for genotype to phenotype mapping.
Home-page: https://github.com/pypa/DeepMap
Author: IRRI South Asia Hub
Author-email: irrisah@gmail.com
Project-URL: Bug Tracker, https://github.com/pypa/DeepMap/issues
Classifier: Programming Language :: Python :: 3
Classifier: License :: OSI Approved :: MIT License
Classifier: Operating System :: OS Independent
Requires-Python: >=3.6
License-File: LICENCE.txt
